{"name": "CompilationUnit", "children": [
  {"name": "PackageDeclaration", "children": [
    {"name": "Name", "children": [
      {"name": "Name", "children": [
        {"name": "Name"}
      ]}
    ]}
  ]}, 
  {"name": "ImportDeclaration", "children": [
    {"name": "Name", "children": [
      {"name": "Name", "children": [
        {"name": "Name"}
      ]}
    ]}
  ]}, 
  {"name": "ImportDeclaration", "children": [
    {"name": "Name", "children": [
      {"name": "Name", "children": [
        {"name": "Name"}
      ]}
    ]}
  ]}, 
  {"name": "ImportDeclaration", "children": [
    {"name": "Name", "children": [
      {"name": "Name", "children": [
        {"name": "Name"}
      ]}
    ]}
  ]}, 
  {"name": "ImportDeclaration", "children": [
    {"name": "Name", "children": [
      {"name": "Name", "children": [
        {"name": "Name"}
      ]}
    ]}
  ]}, 
  {"name": "ImportDeclaration", "children": [
    {"name": "Name", "children": [
      {"name": "Name", "children": [
        {"name": "Name"}
      ]}
    ]}
  ]}, 
  {"name": "ImportDeclaration", "children": [
    {"name": "Name", "children": [
      {"name": "Name", "children": [
        {"name": "Name"}
      ]}
    ]}
  ]}, 
  {"name": "ImportDeclaration", "children": [
    {"name": "Name", "children": [
      {"name": "Name", "children": [
        {"name": "Name"}
      ]}
    ]}
  ]}, 
  {"name": "ImportDeclaration", "children": [
    {"name": "Name", "children": [
      {"name": "Name", "children": [
        {"name": "Name"}
      ]}
    ]}
  ]}, 
  {"name": "ImportDeclaration", "children": [
    {"name": "Name", "children": [
      {"name": "Name", "children": [
        {"name": "Name"}
      ]}
    ]}
  ]}, 
  {"name": "ImportDeclaration", "children": [
    {"name": "Name", "children": [
      {"name": "Name", "children": [
        {"name": "Name", "children": [
          {"name": "Name"}
        ]}
      ]}
    ]}
  ]}, 
  {"name": "ImportDeclaration", "children": [
    {"name": "Name", "children": [
      {"name": "Name", "children": [
        {"name": "Name", "children": [
          {"name": "Name"}
        ]}
      ]}
    ]}
  ]}, 
  {"name": "ImportDeclaration", "children": [
    {"name": "Name", "children": [
      {"name": "Name", "children": [
        {"name": "Name", "children": [
          {"name": "Name"}
        ]}
      ]}
    ]}
  ]}, 
  {"name": "ImportDeclaration", "children": [
    {"name": "Name", "children": [
      {"name": "Name", "children": [
        {"name": "Name", "children": [
          {"name": "Name"}
        ]}
      ]}
    ]}
  ]}, 
  {"name": "ImportDeclaration", "children": [
    {"name": "Name", "children": [
      {"name": "Name", "children": [
        {"name": "Name", "children": [
          {"name": "Name"}
        ]}
      ]}
    ]}
  ]}, 
  {"name": "ImportDeclaration", "children": [
    {"name": "Name", "children": [
      {"name": "Name", "children": [
        {"name": "Name", "children": [
          {"name": "Name"}
        ]}
      ]}
    ]}
  ]}, 
  {"name": "ClassOrInterfaceDeclaration", "children": [
    {"name": "MarkerAnnotationExpr", "children": [
      {"name": "Name"}
    ]}, 
    {"name": "SimpleName"}, 
    {"name": "FieldDeclaration", "children": [
      {"name": "NormalAnnotationExpr", "children": [
        {"name": "Name"}, 
        {"name": "MemberValuePair", "children": [
          {"name": "SimpleName"}, 
          {"name": "StringLiteralExpr"}
        ]}
      ]}, 
      {"name": "VariableDeclarator", "children": [
        {"name": "ClassOrInterfaceType", "children": [
          {"name": "SimpleName"}
        ]}, 
        {"name": "SimpleName"}
      ]}
    ]}, 
    {"name": "MethodDeclaration", "children": [
      {"name": "MarkerAnnotationExpr", "children": [
        {"name": "Name"}
      ]}, 
      {"name": "SimpleName"}, 
      {"name": "Parameter", "children": [
        {"name": "ClassOrInterfaceType", "children": [
          {"name": "SimpleName"}
        ]}, 
        {"name": "SimpleName"}
      ]}, 
      {"name": "VoidType"}, 
      {"name": "BlockStmt", "children": [
        {"name": "LineComment"}
      ]}
    ]}, 
    {"name": "MethodDeclaration", "children": [
      {"name": "MarkerAnnotationExpr", "children": [
        {"name": "Name"}
      ]}, 
      {"name": "SimpleName"}, 
      {"name": "Parameter", "children": [
        {"name": "ClassOrInterfaceType", "children": [
          {"name": "SimpleName"}
        ]}, 
        {"name": "SimpleName"}
      ]}, 
      {"name": "VoidType"}, 
      {"name": "BlockStmt", "children": [
        {"name": "LineComment"}
      ]}
    ]}, 
    {"name": "MethodDeclaration", "children": [
      {"name": "MarkerAnnotationExpr", "children": [
        {"name": "Name"}
      ]}, 
      {"name": "SimpleName"}, 
      {"name": "Parameter", "children": [
        {"name": "ClassOrInterfaceType", "children": [
          {"name": "SimpleName"}
        ]}, 
        {"name": "SimpleName"}
      ]}, 
      {"name": "VoidType"}, 
      {"name": "BlockStmt", "children": [
        {"name": "LineComment"}
      ]}
    ]}, 
    {"name": "MethodDeclaration", "children": [
      {"name": "MarkerAnnotationExpr", "children": [
        {"name": "Name"}
      ]}, 
      {"name": "SimpleName"}, 
      {"name": "Parameter", "children": [
        {"name": "ClassOrInterfaceType", "children": [
          {"name": "SimpleName"}
        ]}, 
        {"name": "SimpleName"}
      ]}, 
      {"name": "VoidType"}, 
      {"name": "BlockStmt", "children": [
        {"name": "LineComment"}
      ]}
    ]}, 
    {"name": "MethodDeclaration", "children": [
      {"name": "MarkerAnnotationExpr", "children": [
        {"name": "Name"}
      ]}, 
      {"name": "SimpleName"}, 
      {"name": "Parameter", "children": [
        {"name": "ClassOrInterfaceType", "children": [
          {"name": "SimpleName"}
        ]}, 
        {"name": "SimpleName"}
      ]}, 
      {"name": "VoidType"}, 
      {"name": "BlockStmt", "children": [
        {"name": "LineComment"}
      ]}
    ]}, 
    {"name": "MethodDeclaration", "children": [
      {"name": "MarkerAnnotationExpr", "children": [
        {"name": "Name"}
      ]}, 
      {"name": "SimpleName"}, 
      {"name": "Parameter", "children": [
        {"name": "ClassOrInterfaceType", "children": [
          {"name": "SimpleName"}
        ]}, 
        {"name": "SimpleName"}
      ]}, 
      {"name": "VoidType"}, 
      {"name": "BlockStmt", "children": [
        {"name": "IfStmt", "children": [
          {"name": "BinaryExpr", "children": [
            {"name": "MethodCallExpr", "children": [
              {"name": "MethodCallExpr", "children": [
                {"name": "NameExpr", "children": [
                  {"name": "SimpleName"}
                ]}, 
                {"name": "SimpleName"}
              ]}, 
              {"name": "SimpleName"}, 
              {"name": "StringLiteralExpr"}
            ]}, 
            {"name": "NullLiteralExpr"}
          ]}, 
          {"name": "ThrowStmt", "children": [
            {"name": "ObjectCreationExpr", "children": [
              {"name": "ClassOrInterfaceType", "children": [
                {"name": "SimpleName"}
              ]}, 
              {"name": "StringLiteralExpr"}
            ]}
          ]}
        ]}, 
        {"name": "ExpressionStmt", "children": [
          {"name": "MethodCallExpr", "children": [
            {"name": "MethodCallExpr", "children": [
              {"name": "NameExpr", "children": [
                {"name": "SimpleName"}
              ]}, 
              {"name": "SimpleName"}
            ]}, 
            {"name": "SimpleName"}, 
            {"name": "StringLiteralExpr"}, 
            {"name": "MethodCallExpr", "children": [
              {"name": "NameExpr", "children": [
                {"name": "SimpleName"}
              ]}, 
              {"name": "SimpleName"}, 
              {"name": "BinaryExpr", "children": [
                {"name": "NameExpr", "children": [
                  {"name": "SimpleName"}
                ]}, 
                {"name": "NullLiteralExpr"}
              ]}
            ]}
          ]}
        ]}
      ]}
    ]}, 
    {"name": "MethodDeclaration", "children": [
      {"name": "MarkerAnnotationExpr", "children": [
        {"name": "Name"}
      ]}, 
      {"name": "SimpleName"}, 
      {"name": "Parameter", "children": [
        {"name": "ClassOrInterfaceType", "children": [
          {"name": "SimpleName"}
        ]}, 
        {"name": "SimpleName"}
      ]}, 
      {"name": "VoidType"}, 
      {"name": "BlockStmt", "children": [
        {"name": "LineComment"}
      ]}
    ]}, 
    {"name": "MethodDeclaration", "children": [
      {"name": "MarkerAnnotationExpr", "children": [
        {"name": "Name"}
      ]}, 
      {"name": "SimpleName"}, 
      {"name": "Parameter", "children": [
        {"name": "ClassOrInterfaceType", "children": [
          {"name": "SimpleName"}
        ]}, 
        {"name": "SimpleName"}
      ]}, 
      {"name": "VoidType"}, 
      {"name": "BlockStmt", "children": [
        {"name": "LineComment"}
      ]}
    ]}, 
    {"name": "MethodDeclaration", "children": [
      {"name": "MarkerAnnotationExpr", "children": [
        {"name": "Name"}
      ]}, 
      {"name": "SimpleName"}, 
      {"name": "Parameter", "children": [
        {"name": "ClassOrInterfaceType", "children": [
          {"name": "SimpleName"}
        ]}, 
        {"name": "SimpleName"}
      ]}, 
      {"name": "VoidType"}, 
      {"name": "BlockStmt", "children": [
        {"name": "LineComment"}
      ]}
    ]}, 
    {"name": "MethodDeclaration", "children": [
      {"name": "MarkerAnnotationExpr", "children": [
        {"name": "Name"}
      ]}, 
      {"name": "SimpleName"}, 
      {"name": "Parameter", "children": [
        {"name": "ClassOrInterfaceType", "children": [
          {"name": "SimpleName"}
        ]}, 
        {"name": "SimpleName"}
      ]}, 
      {"name": "VoidType"}, 
      {"name": "BlockStmt", "children": [
        {"name": "LineComment"}
      ]}
    ]}, 
    {"name": "MethodDeclaration", "children": [
      {"name": "MarkerAnnotationExpr", "children": [
        {"name": "Name"}
      ]}, 
      {"name": "SimpleName"}, 
      {"name": "Parameter", "children": [
        {"name": "ClassOrInterfaceType", "children": [
          {"name": "SimpleName"}
        ]}, 
        {"name": "SimpleName"}
      ]}, 
      {"name": "VoidType"}, 
      {"name": "BlockStmt", "children": [
        {"name": "LineComment"}
      ]}
    ]}, 
    {"name": "MethodDeclaration", "children": [
      {"name": "MarkerAnnotationExpr", "children": [
        {"name": "Name"}
      ]}, 
      {"name": "SimpleName"}, 
      {"name": "Parameter", "children": [
        {"name": "ClassOrInterfaceType", "children": [
          {"name": "SimpleName"}
        ]}, 
        {"name": "SimpleName"}
      ]}, 
      {"name": "VoidType"}, 
      {"name": "BlockStmt", "children": [
        {"name": "LineComment"}
      ]}
    ]}, 
    {"name": "MethodDeclaration", "children": [
      {"name": "MarkerAnnotationExpr", "children": [
        {"name": "Name"}
      ]}, 
      {"name": "SimpleName"}, 
      {"name": "Parameter", "children": [
        {"name": "ClassOrInterfaceType", "children": [
          {"name": "SimpleName"}
        ]}, 
        {"name": "SimpleName"}
      ]}, 
      {"name": "VoidType"}, 
      {"name": "BlockStmt", "children": [
        {"name": "LineComment"}
      ]}
    ]}, 
    {"name": "MethodDeclaration", "children": [
      {"name": "MarkerAnnotationExpr", "children": [
        {"name": "Name"}
      ]}, 
      {"name": "SimpleName"}, 
      {"name": "Parameter", "children": [
        {"name": "ClassOrInterfaceType", "children": [
          {"name": "SimpleName"}
        ]}, 
        {"name": "SimpleName"}
      ]}, 
      {"name": "VoidType"}, 
      {"name": "BlockStmt", "children": [
        {"name": "LineComment"}
      ]}
    ]}, 
    {"name": "MethodDeclaration", "children": [
      {"name": "MarkerAnnotationExpr", "children": [
        {"name": "Name"}
      ]}, 
      {"name": "SimpleName"}, 
      {"name": "Parameter", "children": [
        {"name": "ClassOrInterfaceType", "children": [
          {"name": "SimpleName"}
        ]}, 
        {"name": "SimpleName"}
      ]}, 
      {"name": "VoidType"}, 
      {"name": "BlockStmt", "children": [
        {"name": "LineComment"}
      ]}
    ]}, 
    {"name": "MethodDeclaration", "children": [
      {"name": "MarkerAnnotationExpr", "children": [
        {"name": "Name"}
      ]}, 
      {"name": "SimpleName"}, 
      {"name": "Parameter", "children": [
        {"name": "ClassOrInterfaceType", "children": [
          {"name": "SimpleName"}
        ]}, 
        {"name": "SimpleName"}
      ]}, 
      {"name": "VoidType"}, 
      {"name": "BlockStmt", "children": [
        {"name": "LineComment"}
      ]}
    ]}, 
    {"name": "MethodDeclaration", "children": [
      {"name": "MarkerAnnotationExpr", "children": [
        {"name": "Name"}
      ]}, 
      {"name": "SimpleName"}, 
      {"name": "Parameter", "children": [
        {"name": "ClassOrInterfaceType", "children": [
          {"name": "SimpleName"}
        ]}, 
        {"name": "SimpleName"}
      ]}, 
      {"name": "VoidType"}, 
      {"name": "BlockStmt", "children": [
        {"name": "LineComment"}
      ]}
    ]}, 
    {"name": "MethodDeclaration", "children": [
      {"name": "SimpleName"}, 
      {"name": "Parameter", "children": [
        {"name": "ClassOrInterfaceType", "children": [
          {"name": "SimpleName"}
        ]}, 
        {"name": "SimpleName"}
      ]}, 
      {"name": "VoidType"}, 
      {"name": "BlockStmt", "children": [
        {"name": "LineComment"}
      ]}
    ]}, 
    {"name": "MethodDeclaration", "children": [
      {"name": "SimpleName"}, 
      {"name": "Parameter", "children": [
        {"name": "ClassOrInterfaceType", "children": [
          {"name": "SimpleName"}
        ]}, 
        {"name": "SimpleName"}
      ]}, 
      {"name": "VoidType"}, 
      {"name": "BlockStmt", "children": [
        {"name": "LineComment"}
      ]}
    ]}, 
    {"name": "MethodDeclaration", "children": [
      {"name": "SimpleName"}, 
      {"name": "Parameter", "children": [
        {"name": "ClassOrInterfaceType", "children": [
          {"name": "SimpleName"}
        ]}, 
        {"name": "SimpleName"}
      ]}, 
      {"name": "VoidType"}, 
      {"name": "BlockStmt", "children": [
        {"name": "LineComment"}
      ]}
    ]}, 
    {"name": "ClassOrInterfaceType", "children": [
      {"name": "SimpleName"}
    ]}, 
    {"name": "ClassOrInterfaceType", "children": [
      {"name": "SimpleName"}
    ]}, 
    {"name": "ClassOrInterfaceType", "children": [
      {"name": "SimpleName"}
    ]}, 
    {"name": "ClassOrInterfaceType", "children": [
      {"name": "SimpleName"}
    ]}, 
    {"name": "ClassOrInterfaceType", "children": [
      {"name": "SimpleName"}
    ]}, 
    {"name": "ClassOrInterfaceType", "children": [
      {"name": "SimpleName"}
    ]}, 
    {"name": "ClassOrInterfaceType", "children": [
      {"name": "SimpleName"}
    ]}
  ]}, 
  {"name": "LineComment"}, 
  {"name": "LineComment"}, 
  {"name": "LineComment"}, 
  {"name": "LineComment"}, 
  {"name": "LineComment"}, 
  {"name": "LineComment"}, 
  {"name": "LineComment"}, 
  {"name": "LineComment"}, 
  {"name": "LineComment"}, 
  {"name": "LineComment"}, 
  {"name": "LineComment"}, 
  {"name": "LineComment"}, 
  {"name": "LineComment"}, 
  {"name": "LineComment"}, 
  {"name": "LineComment"}, 
  {"name": "LineComment"}
]}
